emaremes/__init__.py
emaremes/fetch.py
emaremes/plot.py
emaremes/typing_utils.py
emaremes/utils.py
emaremes/ts/__init__.py
emaremes/ts/point.py
emaremes/ts/polygon.py
emaremes-0.0.8.dist-info/METADATA
emaremes-0.0.8.dist-info/WHEEL
emaremes-0.0.8.dist-info/licenses/LICENSE
emaremes-0.0.8.dist-info/RECORD
